comb_testing/__init__.py
comb_testing/__main__.py
comb_testing/biased_algorithm.py
comb_testing/test_suite.py
comb_testing/tuple_set.py
combinatorial_tests_agragland-0.0.4.dist-info/LICENSE
combinatorial_tests_agragland-0.0.4.dist-info/METADATA
combinatorial_tests_agragland-0.0.4.dist-info/WHEEL
combinatorial_tests_agragland-0.0.4.dist-info/top_level.txt
combinatorial_tests_agragland-0.0.4.dist-info/RECORD
