Metadata-Version: 2.1
Name: combinatorial-tests-agragland
Version: 0.0.4
Summary: Creates combinatorial test suites
Home-page: https://github.com/agragland/comb-test-library
Author: Andrew Ragland
Author-email: agragland00@gmail.com
License: MIT
Platform: UNKNOWN
Classifier: License :: OSI Approved :: MIT License
Classifier: Programming Language :: Python :: 3
Requires-Python: >=3.8
